autoslicer/AutoSlicer.py
autoslicer/__init__.py
autoslicer-2.0.0.dist-info/METADATA
autoslicer-2.0.0.dist-info/WHEEL
autoslicer-2.0.0.dist-info/top_level.txt
autoslicer-2.0.0.dist-info/RECORD
