Metadata-Version: 2.1
Name: autoslicer
Version: 2.0.0
Summary: An automated tool for medical image processing with DICOM to NIfTI conversion, segmentation, and analysis.
Home-page: 
Author: Bruce Yang
Author-email: bruceyang022059@gmail.com
License: MIT
Classifier: Programming Language :: Python :: 3
Classifier: License :: OSI Approved :: MIT License
Classifier: Operating System :: OS Independent
Requires-Python: >=3.6
Requires-Dist: SimpleITK
Requires-Dist: nibabel
Requires-Dist: numpy
Requires-Dist: torch
Requires-Dist: totalsegmentator
Requires-Dist: vtk
